{
    "SavePath": "Breakthroughs",
    "SaveName": "Breakthrough",
    "ImportedConstants": [ "SharedResources.json" ],
    "ImportedPrototypes": [ "SharedResources.json" ],
    "ImportedItems": [ "BreakthroughItems.json" ],
    "Blueprint": 
    {
        "Prototype": "MiniCardBlueprint",
        "Elements": 
        [
            {
                "Prototype": "MiniCardImage",
                "Source": "^CardMod"
            },
            {
                "Prototype": "MiniCardName",
                "Content": "~Name"
            },
            {
                "Prototype": "FlashyText",
                "Content": "~Target",
                "X": "72",
                "Y": "170",
                "Width": "300",
                "Height": "130"  
            },
            {
                "Prototype": "FlashyText",
                "Content": "~Cost",
                "X": "380",
                "Y": "200",
                "Width": "140",
                "Height": "70"
            },  
            {
                "Prototype": "DescriptionText",
                "Content": "~Text",
                "X": "72",
                "Y": "480",
                "Width": "448",
                "Height": "300"
            },
            {
                "Prototype": "FlashyText",
                "Content": "~StageOneRebate",
                "X": "72",
                "Y": "310",
                "Width": "448",
                "Height": "80"
            },
            {
                "Prototype": "FlashyText",
                "Content": "~StageTwoRebate",
                "X": "72",
                "Y": "400",
                "Width": "448",
                "Height": "80"
            }
        ]
    }
}